{"name":"Tic Tac Toe with AI inbuilt","tagline":"Tic tac toe with artificial intelligence and timeout options","body":"Welcome to codes.\r\n\r\nTic tac toe with artificial intelligence and timeout options\r\n\r\nPages are under construction so plz visit later.<br>\r\nor go to this site.\r\n[www.infotimes.tk](www.infotimes.tk)\r\n\r\n\r\n\r\n\r\nRegards,<br>\r\n**RAJEEV RANJAN** (OWNER OF THIS REPOSITORY)<br>\r\nJAVA DEVELOPER<br>\r\nNIIT, THANE<br>","google":"","note":"Don't delete this file! It's used internally to help with page regeneration."}